{"5":[{"text":"loved","number":"g25"},{"text":"sister","number":"g79"},{"text":"her","number":"g846"},{"text":"Now","number":"g1161"},{"text":"Jesus","number":"g2424"},{"text":"and","number":"g2532"},{"text":"and","number":"g2532"},{"text":"Lazarus","number":"g2976"},{"text":"Martha","number":"g3136"}],"55":[{"text":"purify","number":"g48"},{"text":"went","number":"g305"},{"text":"And","number":"g1161"},{"text":"themselves","number":"g1438"},{"text":"nigh at hand","number":"g1451"},{"text":"up","number":"g1519"},{"text":"out of","number":"g1537"},{"text":"was","number":"g2258"},{"text":"to Jerusalem","number":"g2414"},{"text":"to","number":"g2443"},{"text":"the Jews","number":"g2453"},{"text":"and","number":"g2532"},{"text":"passover","number":"g3957"},{"text":"the passover","number":"g3957"},{"text":"many","number":"g4183"},{"text":"before","number":"g4253"},{"text":"the country","number":"g5561"}],"16":[{"text":"Let us","number":"g71"},{"text":"go","number":"g71"},{"text":"may die","number":"g599"},{"text":"him","number":"g846"},{"text":"Didymus","number":"g1324"},{"text":"said","number":"g2036"},{"text":"we","number":"g2249"},{"text":"Thomas","number":"g2381"},{"text":"that","number":"g2443"},{"text":"also","number":"g2532"},{"text":"is called","number":"g3004"},{"text":"with","number":"g3326"},{"text":"which","number":"g3588"},{"text":"Then","number":"g3767"},{"text":"unto his fellowdisciples","number":"g4827"}],"7":[{"text":"Let us go","number":"g71"},{"text":"into","number":"g1519"},{"text":"Then","number":"g1899"},{"text":"Judaea","number":"g2449"},{"text":"saith he","number":"g3004"},{"text":"to his disciples","number":"g3101"},{"text":"after","number":"g3326"},{"text":"again","number":"g3825"},{"text":"that","number":"g5124"}],"15":[{"text":"let us go","number":"g71"},{"text":"nevertheless","number":"g235"},{"text":"him","number":"g846"},{"text":"for","number":"g1223"},{"text":"there","number":"g1563"},{"text":"I was","number":"g2252"},{"text":"to the intent","number":"g2443"},{"text":"And","number":"g2532"},{"text":"that","number":"g3754"},{"text":"not","number":"g3756"},{"text":"ye may believe","number":"g4100"},{"text":"unto","number":"g4314"},{"text":"your sakes","number":"g5209"},{"text":"I am glad","number":"g5463"}],"3":[{"text":"his sisters","number":"g79"},{"text":"sent","number":"g649"},{"text":"is sick","number":"g770"},{"text":"him","number":"g846"},{"text":"behold","number":"g2396"},{"text":"Lord","number":"g2962"},{"text":"saying","number":"g3004"},{"text":"he whom","number":"g3739"},{"text":"Therefore","number":"g3767"},{"text":"unto","number":"g4314"},{"text":"thou lovest","number":"g5368"}],"1":[{"text":"sister","number":"g79"},{"text":"of","number":"g575"},{"text":"sick","number":"g770"},{"text":"her","number":"g846"},{"text":"Bethany","number":"g963"},{"text":"Now","number":"g1161"},{"text":"man was","number":"g2258"},{"text":"and","number":"g2532"},{"text":"the town","number":"g2968"},{"text":"named Lazarus","number":"g2976"},{"text":"Martha","number":"g3136"},{"text":"of Mary","number":"g3137"},{"text":"a certain","number":"g5100"}],"28":[{"text":"sister","number":"g79"},{"text":"she went her way","number":"g565"},{"text":"her","number":"g848"},{"text":"The Master","number":"g1320"},{"text":"said","number":"g2036"},{"text":"saying","number":"g2036"},{"text":"when she had","number":"g2036"},{"text":"And","number":"g2532"},{"text":"and","number":"g2532"},{"text":"and","number":"g2532"},{"text":"secretly","number":"g2977"},{"text":"Mary","number":"g3137"},{"text":"is come","number":"g3918"},{"text":"thee","number":"g4571"},{"text":"so","number":"g5023"},{"text":"called","number":"g5455"},{"text":"calleth for","number":"g5455"}],"39":[{"text":"the sister","number":"g79"},{"text":"Take ye away","number":"g142"},{"text":"unto him","number":"g846"},{"text":"for","number":"g1063"},{"text":"he hath been","number":"g2076"},{"text":"by this time","number":"g2235"},{"text":"of him that was dead","number":"g2348"},{"text":"Jesus","number":"g2424"},{"text":"Lord","number":"g2962"},{"text":"said","number":"g3004"},{"text":"saith","number":"g3004"},{"text":"the stone","number":"g3037"},{"text":"Martha","number":"g3136"},{"text":"he stinketh","number":"g3605"},{"text":"dead four days","number":"g5066"}],"19":[{"text":"brother","number":"g80"},{"text":"their","number":"g846"},{"text":"them","number":"g846"},{"text":"of","number":"g1537"},{"text":"came","number":"g2064"},{"text":"to","number":"g2443"},{"text":"the Jews","number":"g2453"},{"text":"And","number":"g2532"},{"text":"and","number":"g2532"},{"text":"Martha","number":"g3136"},{"text":"Mary","number":"g3137"},{"text":"comfort","number":"g3888"},{"text":"concerning","number":"g4012"},{"text":"many","number":"g4183"},{"text":"to","number":"g4314"}],"2":[{"text":"brother","number":"g80"},{"text":"anointed","number":"g218"},{"text":"was sick","number":"g770"},{"text":"his","number":"g846"},{"text":"with her","number":"g848"},{"text":"wiped","number":"g1591"},{"text":"(It was","number":"g2258"},{"text":"hair","number":"g2359"},{"text":"and","number":"g2532"},{"text":"the Lord","number":"g2962"},{"text":"Lazarus","number":"g2976"},{"text":"that Mary","number":"g3137"},{"text":"with ointment","number":"g3464"},{"text":"which","number":"g3588"},{"text":"whose","number":"g3739"},{"text":"feet","number":"g4228"}],"21":[{"text":"brother","number":"g80"},{"text":"if","number":"g1487"},{"text":"said","number":"g2036"},{"text":"thou hadst been","number":"g2258"},{"text":"died","number":"g2348"},{"text":"had","number":"g2348"},{"text":"Jesus","number":"g2424"},{"text":"Lord","number":"g2962"},{"text":"Martha","number":"g3136"},{"text":"my","number":"g3450"},{"text":"not","number":"g3756"},{"text":"Then","number":"g3767"},{"text":"unto","number":"g4314"},{"text":"here","number":"g5602"}],"23":[{"text":"brother","number":"g80"},{"text":"shall rise again","number":"g450"},{"text":"unto her","number":"g846"},{"text":"Jesus","number":"g2424"},{"text":"saith","number":"g3004"},{"text":"Thy","number":"g4675"}],"32":[{"text":"brother","number":"g80"},{"text":"had","number":"g302"},{"text":"died","number":"g599"},{"text":"him","number":"g846"},{"text":"his","number":"g846"},{"text":"unto him","number":"g846"},{"text":"if","number":"g1487"},{"text":"and saw","number":"g1492"},{"text":"at","number":"g1519"},{"text":"was come","number":"g2064"},{"text":"thou hadst been","number":"g2258"},{"text":"was","number":"g2258"},{"text":"Jesus","number":"g2424"},{"text":"Lord","number":"g2962"},{"text":"saying","number":"g3004"},{"text":"Mary","number":"g3137"},{"text":"my","number":"g3450"},{"text":"where","number":"g3699"},{"text":"not","number":"g3756"},{"text":"Then","number":"g3767"},{"text":"she fell down","number":"g4098"},{"text":"feet","number":"g4228"},{"text":"here","number":"g5602"},{"text":"when","number":"g5613"}],"41":[{"text":"lifted","number":"g142"},{"text":"they took away","number":"g142"},{"text":"thou hast heard","number":"g191"},{"text":"up","number":"g507"},{"text":"And","number":"g1161"},{"text":"said","number":"g2036"},{"text":"I thank","number":"g2168"},{"text":"was","number":"g2258"},{"text":"the dead","number":"g2348"},{"text":"Jesus","number":"g2424"},{"text":"and","number":"g2532"},{"text":"laid","number":"g2749"},{"text":"the stone","number":"g3037"},{"text":"me","number":"g3450"},{"text":"that","number":"g3754"},{"text":"from the place where","number":"g3757"},{"text":"Then","number":"g3767"},{"text":"his eyes","number":"g3788"},{"text":"Father","number":"g3962"},{"text":"thee","number":"g4671"}],"48":[{"text":"take away","number":"g142"},{"text":"him","number":"g846"},{"text":"him","number":"g846"},{"text":"alone","number":"g863"},{"text":"we let","number":"g863"},{"text":"If","number":"g1437"},{"text":"nation","number":"g1484"},{"text":"on","number":"g1519"},{"text":"shall come","number":"g2064"},{"text":"our","number":"g2257"},{"text":"and","number":"g2532"},{"text":"and","number":"g2532"},{"text":"and","number":"g2532"},{"text":"both","number":"g2532"},{"text":"thus","number":"g3779"},{"text":"all","number":"g3956"},{"text":"men will believe","number":"g4100"},{"text":"the Romans","number":"g4514"},{"text":"place","number":"g5117"}],"22":[{"text":"thou wilt ask","number":"g154"},{"text":"But","number":"g235"},{"text":"will give","number":"g1325"},{"text":"I know","number":"g1492"},{"text":"God","number":"g2316"},{"text":"of God","number":"g2316"},{"text":"that even","number":"g2532"},{"text":"now","number":"g3568"},{"text":"whatsoever","number":"g3754"},{"text":"it thee","number":"g4671"}],"31":[{"text":"followed","number":"g190"},{"text":"she rose up","number":"g450"},{"text":"her","number":"g846"},{"text":"her","number":"g846"},{"text":"her","number":"g846"},{"text":"when they saw","number":"g1492"},{"text":"unto","number":"g1519"},{"text":"there","number":"g1563"},{"text":"in","number":"g1722"},{"text":"went out","number":"g1831"},{"text":"to","number":"g2443"},{"text":"The Jews","number":"g2453"},{"text":"and","number":"g2532"},{"text":"and","number":"g2532"},{"text":"weep","number":"g2799"},{"text":"saying","number":"g3004"},{"text":"Mary","number":"g3137"},{"text":"with","number":"g3326"},{"text":"the grave","number":"g3419"},{"text":"which","number":"g3588"},{"text":"the house","number":"g3614"},{"text":"that","number":"g3754"},{"text":"then","number":"g3767"},{"text":"comforted","number":"g3888"},{"text":"hastily","number":"g5030"},{"text":"She goeth","number":"g5217"},{"text":"were","number":"g5607"}],"6":[{"text":"he had heard","number":"g191"},{"text":"he was sick","number":"g770"},{"text":"two","number":"g1417"},{"text":"in","number":"g1722"},{"text":"days","number":"g2250"},{"text":"he was","number":"g2258"},{"text":"he abode","number":"g3306"},{"text":"where","number":"g3739"},{"text":"that","number":"g3754"},{"text":"therefore","number":"g3767"},{"text":"the same place","number":"g5117"},{"text":"still","number":"g5119"},{"text":"When","number":"g5613"}],"29":[{"text":"heard","number":"g191"},{"text":"him","number":"g846"},{"text":"that she arose","number":"g1453"},{"text":"she","number":"g1565"},{"text":"came","number":"g2064"},{"text":"and","number":"g2532"},{"text":"unto","number":"g4314"},{"text":"quickly","number":"g5035"},{"text":"As soon as","number":"g5613"}],"4":[{"text":"heard","number":"g191"},{"text":"but","number":"g235"},{"text":"sickness","number":"g769"},{"text":"When","number":"g1161"},{"text":"thereby","number":"g1223"},{"text":"the glory","number":"g1391"},{"text":"might be glorified","number":"g1392"},{"text":"that he said","number":"g2036"},{"text":"is","number":"g2076"},{"text":"death","number":"g2288"},{"text":"of God","number":"g2316"},{"text":"of God","number":"g2316"},{"text":"Jesus","number":"g2424"},{"text":"that","number":"g2443"},{"text":"not","number":"g3756"},{"text":"This","number":"g3778"},{"text":"unto","number":"g4314"},{"text":"the Son","number":"g5207"},{"text":"for","number":"g5228"}],"20":[{"text":"she heard","number":"g191"},{"text":"him","number":"g846"},{"text":"but","number":"g1161"},{"text":"still in","number":"g1722"},{"text":"was coming","number":"g2064"},{"text":"Jesus","number":"g2424"},{"text":"sat","number":"g2516"},{"text":"Martha","number":"g3136"},{"text":"Mary","number":"g3137"},{"text":"the house","number":"g3624"},{"text":"that","number":"g3754"},{"text":"Then","number":"g3767"},{"text":"went and met","number":"g5221"},{"text":"as soon as","number":"g5613"}],"42":[{"text":"thou hearest","number":"g191"},{"text":"but","number":"g235"},{"text":"hast sent","number":"g649"},{"text":"And","number":"g1161"},{"text":"because","number":"g1223"},{"text":"I","number":"g1473"},{"text":"knew","number":"g1492"},{"text":"I said","number":"g2036"},{"text":"it that","number":"g2443"},{"text":"me","number":"g3165"},{"text":"me","number":"g3450"},{"text":"which","number":"g3588"},{"text":"that","number":"g3754"},{"text":"that","number":"g3754"},{"text":"of the people","number":"g3793"},{"text":"always","number":"g3842"},{"text":"stand by","number":"g4026"},{"text":"they may believe","number":"g4100"},{"text":"thou","number":"g4771"}],"11":[{"text":"but","number":"g235"},{"text":"he","number":"g846"},{"text":"him","number":"g846"},{"text":"unto them","number":"g846"},{"text":"I may awake","number":"g1852"},{"text":"out of sleep","number":"g1852"},{"text":"said","number":"g2036"},{"text":"Our","number":"g2257"},{"text":"that","number":"g2443"},{"text":"and","number":"g2532"},{"text":"sleepeth","number":"g2837"},{"text":"Lazarus","number":"g2976"},{"text":"he saith","number":"g3004"},{"text":"after","number":"g3326"},{"text":"I go","number":"g4198"},{"text":"These things","number":"g5023"},{"text":"that","number":"g5124"},{"text":"friend","number":"g5384"}],"30":[{"text":"but","number":"g235"},{"text":"him","number":"g846"},{"text":"Now","number":"g1161"},{"text":"into","number":"g1519"},{"text":"in","number":"g1722"},{"text":"come","number":"g2064"},{"text":"was","number":"g2064"},{"text":"was","number":"g2258"},{"text":"Jesus","number":"g2424"},{"text":"the town","number":"g2968"},{"text":"Martha","number":"g3136"},{"text":"where","number":"g3699"},{"text":"not yet","number":"g3768"},{"text":"that place","number":"g5117"},{"text":"met","number":"g5221"}],"51":[{"text":"but","number":"g235"},{"text":"of","number":"g575"},{"text":"die","number":"g599"},{"text":"high priest","number":"g749"},{"text":"And","number":"g1161"},{"text":"himself","number":"g1438"},{"text":"nation","number":"g1484"},{"text":"that","number":"g1565"},{"text":"year","number":"g1763"},{"text":"spake he","number":"g2036"},{"text":"Jesus","number":"g2424"},{"text":"should","number":"g3195"},{"text":"that","number":"g3754"},{"text":"not","number":"g3756"},{"text":"he prophesied","number":"g4395"},{"text":"this","number":"g5124"},{"text":"for that","number":"g5228"},{"text":"being","number":"g5607"}],"52":[{"text":"but","number":"g235"},{"text":"that were scattered abroad","number":"g1287"},{"text":"nation","number":"g1484"},{"text":"in","number":"g1519"},{"text":"one","number":"g1520"},{"text":"of God","number":"g2316"},{"text":"that","number":"g2443"},{"text":"And","number":"g2532"},{"text":"also","number":"g2532"},{"text":"only","number":"g3440"},{"text":"not","number":"g3756"},{"text":"he should gather together","number":"g4863"},{"text":"the children","number":"g5043"},{"text":"for that","number":"g5228"}],"54":[{"text":"but","number":"g235"},{"text":"went","number":"g565"},{"text":"his","number":"g848"},{"text":"continued","number":"g1304"},{"text":"near","number":"g1451"},{"text":"into","number":"g1519"},{"text":"unto","number":"g1519"},{"text":"thence","number":"g1564"},{"text":"among","number":"g1722"},{"text":"to the wilderness","number":"g2048"},{"text":"no more","number":"g2089"},{"text":"Ephraim","number":"g2187"},{"text":"Jesus","number":"g2424"},{"text":"the Jews","number":"g2453"},{"text":"and there","number":"g2546"},{"text":"called","number":"g3004"},{"text":"disciples","number":"g3101"},{"text":"with","number":"g3326"},{"text":"therefore","number":"g3767"},{"text":"openly","number":"g3954"},{"text":"walked","number":"g4043"},{"text":"a city","number":"g4172"},{"text":"a country","number":"g5561"}],"56":[{"text":"themselves","number":"g240"},{"text":"think","number":"g1380"},{"text":"to","number":"g1519"},{"text":"in","number":"g1722"},{"text":"the feast","number":"g1859"},{"text":"come","number":"g2064"},{"text":"he will","number":"g2064"},{"text":"sought they for","number":"g2212"},{"text":"the temple","number":"g2411"},{"text":"Jesus","number":"g2424"},{"text":"as they stood","number":"g2476"},{"text":"and","number":"g2532"},{"text":"spake","number":"g3004"},{"text":"among","number":"g3326"},{"text":"not","number":"g3364"},{"text":"that","number":"g3754"},{"text":"Then","number":"g3767"},{"text":"What","number":"g5101"},{"text":"ye","number":"g5213"}],"24":[{"text":"the resurrection","number":"g386"},{"text":"he shall rise again","number":"g450"},{"text":"unto him","number":"g846"},{"text":"I know","number":"g1492"},{"text":"at","number":"g1722"},{"text":"in","number":"g1722"},{"text":"the last","number":"g2078"},{"text":"day","number":"g2250"},{"text":"saith","number":"g3004"},{"text":"Martha","number":"g3136"},{"text":"that","number":"g3754"}],"25":[{"text":"the resurrection","number":"g386"},{"text":"he were dead","number":"g599"},{"text":"unto her","number":"g846"},{"text":"I","number":"g1473"},{"text":"am","number":"g1510"},{"text":"in","number":"g1519"},{"text":"me","number":"g1691"},{"text":"said","number":"g2036"},{"text":"yet shall he live","number":"g2198"},{"text":"the life","number":"g2222"},{"text":"Jesus","number":"g2424"},{"text":"and","number":"g2532"},{"text":"though","number":"g2579"},{"text":"he that believeth","number":"g4100"}],"47":[{"text":"man","number":"g444"},{"text":"the chief priests","number":"g749"},{"text":"and","number":"g2532"},{"text":"and","number":"g2532"},{"text":"said","number":"g3004"},{"text":"for","number":"g3754"},{"text":"Then","number":"g3767"},{"text":"this","number":"g3778"},{"text":"do we","number":"g4160"},{"text":"doeth","number":"g4160"},{"text":"many","number":"g4183"},{"text":"miracles","number":"g4592"},{"text":"gathered","number":"g4863"},{"text":"a council","number":"g4892"},{"text":"What","number":"g5101"},{"text":"the Pharisees","number":"g5330"}],"50":[{"text":"man","number":"g444"},{"text":"should die","number":"g599"},{"text":"perish","number":"g622"},{"text":"consider","number":"g1260"},{"text":"nation","number":"g1484"},{"text":"one","number":"g1520"},{"text":"for us","number":"g2254"},{"text":"that","number":"g2443"},{"text":"and","number":"g2532"},{"text":"the people","number":"g2992"},{"text":"not","number":"g3361"},{"text":"that the whole","number":"g3650"},{"text":"that","number":"g3754"},{"text":"Nor","number":"g3761"},{"text":"it is expedient","number":"g4851"},{"text":"for","number":"g5228"}],"37":[{"text":"opened","number":"g455"},{"text":"have died","number":"g599"},{"text":"should","number":"g599"},{"text":"them","number":"g846"},{"text":"And","number":"g1161"},{"text":"Could","number":"g1410"},{"text":"of","number":"g1537"},{"text":"said","number":"g2036"},{"text":"that","number":"g2443"},{"text":"even","number":"g2532"},{"text":"not","number":"g3361"},{"text":"which","number":"g3588"},{"text":"not","number":"g3756"},{"text":"this man","number":"g3778"},{"text":"this man","number":"g3778"},{"text":"the eyes","number":"g3788"},{"text":"have caused","number":"g4160"},{"text":"some","number":"g5100"},{"text":"of the blind","number":"g5185"}],"46":[{"text":"went their ways","number":"g565"},{"text":"them","number":"g846"},{"text":"them","number":"g846"},{"text":"But","number":"g1161"},{"text":"of","number":"g1537"},{"text":"told","number":"g2036"},{"text":"Jesus","number":"g2424"},{"text":"and","number":"g2532"},{"text":"what things","number":"g3739"},{"text":"had done","number":"g4160"},{"text":"to","number":"g4314"},{"text":"some","number":"g5100"},{"text":"the Pharisees","number":"g5330"}],"53":[{"text":"from","number":"g575"},{"text":"put","number":"g615"},{"text":"to death","number":"g615"},{"text":"him","number":"g846"},{"text":"that","number":"g1565"},{"text":"day","number":"g2250"},{"text":"for to","number":"g2443"},{"text":"Then","number":"g3767"},{"text":"forth they took counsel together","number":"g4823"}],"18":[{"text":"off","number":"g575"},{"text":"Bethany","number":"g963"},{"text":"Now","number":"g1161"},{"text":"fifteen","number":"g1178"},{"text":"nigh","number":"g1451"},{"text":"was","number":"g2258"},{"text":"unto Jerusalem","number":"g2414"},{"text":"furlongs","number":"g4712"},{"text":"about","number":"g5613"}],"26":[{"text":"die","number":"g599"},{"text":"shall","number":"g599"},{"text":"in","number":"g1519"},{"text":"me","number":"g1691"},{"text":"liveth","number":"g2198"},{"text":"And","number":"g2532"},{"text":"and","number":"g2532"},{"text":"never","number":"g3364"},{"text":"whosoever","number":"g3956"},{"text":"Believest thou","number":"g4100"},{"text":"believeth","number":"g4100"},{"text":"this","number":"g5124"}],"14":[{"text":"is dead","number":"g599"},{"text":"unto them","number":"g846"},{"text":"said","number":"g2036"},{"text":"Jesus","number":"g2424"},{"text":"Lazarus","number":"g2976"},{"text":"plainly","number":"g3954"},{"text":"Then","number":"g5119"}],"9":[{"text":"answered","number":"g611"},{"text":"he seeth","number":"g991"},{"text":"twelve","number":"g1427"},{"text":"If","number":"g1437"},{"text":"Are there","number":"g1526"},{"text":"in","number":"g1722"},{"text":"in the day","number":"g2250"},{"text":"the day","number":"g2250"},{"text":"Jesus","number":"g2424"},{"text":"world","number":"g2889"},{"text":"because","number":"g3754"},{"text":"not","number":"g3756"},{"text":"not","number":"g3780"},{"text":"walk","number":"g4043"},{"text":"he stumbleth","number":"g4350"},{"text":"any man","number":"g5100"},{"text":"of this","number":"g5127"},{"text":"the light","number":"g5457"},{"text":"hours","number":"g5610"}],"57":[{"text":"the chief priests","number":"g749"},{"text":"him","number":"g846"},{"text":"knew","number":"g1097"},{"text":"Now","number":"g1161"},{"text":"had given","number":"g1325"},{"text":"if","number":"g1437"},{"text":"a commandment","number":"g1785"},{"text":"he were","number":"g2076"},{"text":"that","number":"g2443"},{"text":"and","number":"g2532"},{"text":"both","number":"g2532"},{"text":"he should shew","number":"g3377"},{"text":"it that","number":"g3704"},{"text":"they might take","number":"g4084"},{"text":"where","number":"g4226"},{"text":"any man","number":"g5100"},{"text":"the Pharisees","number":"g5330"}],"49":[{"text":"the high priest","number":"g749"},{"text":"them","number":"g846"},{"text":"unto them","number":"g846"},{"text":"And","number":"g1161"},{"text":"know","number":"g1492"},{"text":"one","number":"g1520"},{"text":"of","number":"g1537"},{"text":"that same","number":"g1565"},{"text":"year","number":"g1763"},{"text":"said","number":"g2036"},{"text":"named Caiaphas","number":"g2533"},{"text":"nothing at all","number":"g3756"},{"text":"Ye","number":"g5210"},{"text":"being","number":"g5607"}],"33":[{"text":"her","number":"g846"},{"text":"with her","number":"g846"},{"text":"saw","number":"g1492"},{"text":"he groaned","number":"g1690"},{"text":"Jesus","number":"g2424"},{"text":"the Jews","number":"g2453"},{"text":"and","number":"g2532"},{"text":"and","number":"g2532"},{"text":"also weeping","number":"g2799"},{"text":"weeping","number":"g2799"},{"text":"therefore","number":"g3767"},{"text":"in the spirit","number":"g4151"},{"text":"which came","number":"g4905"},{"text":"was troubled","number":"g5015"},{"text":"When","number":"g5613"}],"10":[{"text":"him","number":"g846"},{"text":"But","number":"g1161"},{"text":"if","number":"g1437"},{"text":"in","number":"g1722"},{"text":"in","number":"g1722"},{"text":"there is","number":"g2076"},{"text":"the night","number":"g3571"},{"text":"because","number":"g3754"},{"text":"no","number":"g3756"},{"text":"walk","number":"g4043"},{"text":"he stumbleth","number":"g4350"},{"text":"a man","number":"g5100"},{"text":"light","number":"g5457"}],"34":[{"text":"him","number":"g846"},{"text":"unto him","number":"g846"},{"text":"see","number":"g1492"},{"text":"said","number":"g2036"},{"text":"come","number":"g2064"},{"text":"And","number":"g2532"},{"text":"and","number":"g2532"},{"text":"Lord","number":"g2962"},{"text":"They said","number":"g3004"},{"text":"Where","number":"g4226"},{"text":"have ye laid","number":"g5087"}],"36":[{"text":"him","number":"g846"},{"text":"Behold","number":"g2396"},{"text":"the Jews","number":"g2453"},{"text":"said","number":"g3004"},{"text":"Then","number":"g3767"},{"text":"how","number":"g4459"},{"text":"he loved","number":"g5368"}],"44":[{"text":"him","number":"g846"},{"text":"his","number":"g846"},{"text":"unto them","number":"g846"},{"text":"let him","number":"g863"},{"text":"bound","number":"g1210"},{"text":"came forth","number":"g1831"},{"text":"he that was dead","number":"g2348"},{"text":"Jesus","number":"g2424"},{"text":"And","number":"g2532"},{"text":"and","number":"g2532"},{"text":"and","number":"g2532"},{"text":"and","number":"g2532"},{"text":"with graveclothes","number":"g2750"},{"text":"saith","number":"g3004"},{"text":"Loose","number":"g3089"},{"text":"face","number":"g3799"},{"text":"was bound about","number":"g4019"},{"text":"foot","number":"g4228"},{"text":"with a napkin","number":"g4676"},{"text":"go","number":"g5217"},{"text":"hand","number":"g5495"}],"45":[{"text":"him","number":"g846"},{"text":"on","number":"g1519"},{"text":"of","number":"g1537"},{"text":"came","number":"g2064"},{"text":"had seen","number":"g2300"},{"text":"Jesus","number":"g2424"},{"text":"the Jews","number":"g2453"},{"text":"and","number":"g2532"},{"text":"Mary","number":"g3137"},{"text":"which","number":"g3588"},{"text":"the things which","number":"g3739"},{"text":"Then","number":"g3767"},{"text":"believed","number":"g4100"},{"text":"did","number":"g4160"},{"text":"many","number":"g4183"},{"text":"to","number":"g4314"}],"12":[{"text":"his","number":"g846"},{"text":"if","number":"g1487"},{"text":"said","number":"g2036"},{"text":"he sleep","number":"g2837"},{"text":"Lord","number":"g2962"},{"text":"disciples","number":"g3101"},{"text":"Then","number":"g3767"},{"text":"he shall do well","number":"g4982"}],"13":[{"text":"his","number":"g846"},{"text":"Howbeit","number":"g1161"},{"text":"but","number":"g1161"},{"text":"thought","number":"g1380"},{"text":"they","number":"g1565"},{"text":"spake","number":"g2046"},{"text":"death","number":"g2288"},{"text":"Jesus","number":"g2424"},{"text":"taking of rest","number":"g2838"},{"text":"he had spoken","number":"g3004"},{"text":"that","number":"g3754"},{"text":"of","number":"g4012"},{"text":"of","number":"g4012"},{"text":"in sleep","number":"g5258"}],"38":[{"text":"it","number":"g846"},{"text":"himself","number":"g1438"},{"text":"to","number":"g1519"},{"text":"groaning","number":"g1690"},{"text":"in","number":"g1722"},{"text":"upon","number":"g1909"},{"text":"lay","number":"g1945"},{"text":"cometh","number":"g2064"},{"text":"It was","number":"g2258"},{"text":"Jesus","number":"g2424"},{"text":"and","number":"g2532"},{"text":"a stone","number":"g3037"},{"text":"the grave","number":"g3419"},{"text":"therefore","number":"g3767"},{"text":"again","number":"g3825"},{"text":"a cave","number":"g4693"}],"17":[{"text":"that he","number":"g846"},{"text":"lain in","number":"g1722"},{"text":"came","number":"g2064"},{"text":"he found","number":"g2147"},{"text":"had","number":"g2192"},{"text":"already","number":"g2235"},{"text":"days","number":"g2250"},{"text":"when Jesus","number":"g2424"},{"text":"the grave","number":"g3419"},{"text":"Then","number":"g3767"},{"text":"four","number":"g5064"}],"40":[{"text":"unto her","number":"g846"},{"text":"the glory","number":"g1391"},{"text":"if","number":"g1437"},{"text":"Said I","number":"g2036"},{"text":"of God","number":"g2316"},{"text":"Jesus","number":"g2424"},{"text":"saith","number":"g3004"},{"text":"thou shouldest see","number":"g3700"},{"text":"that","number":"g3754"},{"text":"not","number":"g3756"},{"text":"thou wouldest believe","number":"g4100"},{"text":"unto thee","number":"g4671"}],"27":[{"text":"unto him","number":"g846"},{"text":"I","number":"g1473"},{"text":"art","number":"g1488"},{"text":"into","number":"g1519"},{"text":"should come","number":"g2064"},{"text":"of God","number":"g2316"},{"text":"the world","number":"g2889"},{"text":"Lord","number":"g2962"},{"text":"She saith","number":"g3004"},{"text":"Yea","number":"g3483"},{"text":"which","number":"g3588"},{"text":"that","number":"g3754"},{"text":"believe","number":"g4100"},{"text":"thou","number":"g4771"},{"text":"the Son","number":"g5207"},{"text":"the Christ","number":"g5547"}],"8":[{"text":"unto him","number":"g846"},{"text":"thither","number":"g1563"},{"text":"sought","number":"g2212"},{"text":"the Jews","number":"g2453"},{"text":"and","number":"g2532"},{"text":"say","number":"g3004"},{"text":"to stone","number":"g3034"},{"text":"His disciples","number":"g3101"},{"text":"of late","number":"g3568"},{"text":"again","number":"g3825"},{"text":"Master","number":"g4461"},{"text":"thee","number":"g4571"},{"text":"goest thou","number":"g5217"}],"35":[{"text":"wept","number":"g1145"},{"text":"Jesus","number":"g2424"}],"43":[{"text":"come","number":"g1204"},{"text":"forth","number":"g1854"},{"text":"had spoken","number":"g2036"},{"text":"And","number":"g2532"},{"text":"he cried","number":"g2905"},{"text":"Lazarus","number":"g2976"},{"text":"with a loud","number":"g3173"},{"text":"when he thus","number":"g5023"},{"text":"voice","number":"g5456"}]}